MANIFEST.in
README.md
setup.py
performance_tuner/__init__.py
performance_tuner.egg-info/PKG-INFO
performance_tuner.egg-info/SOURCES.txt
performance_tuner.egg-info/dependency_links.txt
performance_tuner.egg-info/requires.txt
performance_tuner.egg-info/top_level.txt
performance_tuner/precision_recall_tuner/__init__.py
performance_tuner/precision_recall_tuner/precision_recall_tuner.py