Metadata-Version: 2.1
Name: performance-tuner
Version: 0.1
Summary: A set of tools to performance tune your models
Home-page: https://github.com/EricSchles/performance_tuner
Author: Eric Schles
Author-email: ericschles@gmail.com
License: MIT
Platform: UNKNOWN
Classifier: License :: OSI Approved :: MIT License
Classifier: Programming Language :: Python :: 3
Classifier: Programming Language :: Python :: 3.6
Classifier: Programming Language :: Python :: 3.7
